{
  "title": "프리미엄 멤버십",
  "subtitle": "더 많은 문제와 심층 해설로\n합격을 앞당기세요.",
  "price": {
    "label": "이용 요금",
    "amount": "월 9,900원"
  },
  "bank": {
    "label": "입금 계좌",
    "bank_name": "카카오뱅크",
    "account_number": "3333-00-0000000",
    "account_holder": "홍길동"
  },
  "benefits": [
    "✅ 1급·2급 전체 기출문제 무제한 열람",
    "✅ AI 생성 예상 문제 제공",
    "✅ 연도·과목별 상세 필터링",
    "✅ 문제당 전문 해설 제공",
    "🚫 무료: 최대 20문제 / 일반 문제만"
  ],
  "notice": "신청 이메일을 보내시면 관리자 확인 후 즉시 활성화됩니다.",
  "admin_email": "admin@example.com"
}
